coal-labs/lab05_2024335/home_tasks/task1.v
module DivisionT1 (
    input wire clk,
    input wire [7:0] dividend,
    input wire [7:0] divisor,
    output reg [7:0] quotient,
    output reg [7:0] remainder,
    output reg ready
);

    reg [7:0] prev_dividend = 8'h0;
    reg [7:0] prev_divisor = 8'h0;

    reg [15:0] rem_reg;
    reg [15:0] div_reg;
    reg [3:0]  step;
    reg        busy = 0;

    initial begin
        quotient = 0;
        remainder = 0;
        ready = 0;
    end

    always @(posedge clk) begin
        if (dividend != prev_dividend || divisor != prev_divisor) begin
            prev_dividend <= dividend;
            prev_divisor  <= divisor;
            
            rem_reg  <= {8'b0, dividend};
            div_reg  <= {1'b0, divisor, 7'b0};
            quotient <= 8'b0;
            
            step  <= 0;
            busy  <= 1;
            ready <= 0;
        end else if (busy) begin
            if (rem_reg >= div_reg) begin
                rem_reg  <= rem_reg - div_reg;
                quotient <= {quotient[6:0], 1'b1};
                if (step == 7) begin
                    remainder <= rem_reg[7:0] - div_reg[7:0];
                end
            end else begin
                quotient <= {quotient[6:0], 1'b0};
                if (step == 7) begin
                    remainder <= rem_reg[7:0];
                end
            end
            
            div_reg <= div_reg >> 1;
            step    <= step + 1;
            
            if (step == 7) begin
                busy  <= 0;
                ready <= 1;
            end
        end
    end

endmodule

coal-labs/lab05_2024335/task1_tb.v
`timescale 1ns / 1ps

module DivisionT1_tb;

    reg clk;
    reg [7:0] dividend;
    reg [7:0] divisor;

    wire [7:0] quotient;
    wire [7:0] remainder;
    wire ready;

    DivisionT1 Uut (
        .clk(clk),
        .dividend(dividend),
        .divisor(divisor),
        .quotient(quotient),
        .remainder(remainder),
        .ready(ready)
    );

    always #5 clk = ~clk;

    initial begin
        $dumpfile("Lab5.vcd");
        $dumpvars(0, DivisionT1_tb);

        clk = 0;
        dividend = 0;
        divisor = 0;

        #20;
        
        // Test Case 1: 7 / 2
        @(negedge clk);
        dividend = 8'd7;
        divisor = 8'd2;
        
        wait(ready == 1);
        @(posedge clk);
        $display("Test Case: 7 / 2 | Expected: Q=3, R=1 | Actual: Q=%d, R=%d", quotient, remainder);

        // Test Case 2: 100 / 3
        #20;
        @(negedge clk);
        dividend = 8'd100;
        divisor = 8'd3;
        
        wait(ready == 1);
        @(posedge clk);
        $display("Test Case: 100 / 3 | Expected: Q=33, R=1 | Actual: Q=%d, R=%d", quotient, remainder);
        
        // Test Case 3: 45 / 8
        #20;
        @(negedge clk);
        dividend = 8'd45;
        divisor = 8'd8;
        
        wait(ready == 1);
        @(posedge clk);
        $display("Test Case: 45 / 8 | Expected: Q=5, R=5 | Actual: Q=%d, R=%d", quotient, remainder);

        // Test Case 4: 75 / 4
        #20;
        @(negedge clk);
        dividend = 8'd75;
        divisor = 8'd4;
        
        wait(ready == 1);
        @(posedge clk);
        $display("Test Case: 75 / 4 | Expected: Q=18, R=3 | Actual: Q=%d, R=%d", quotient, remainder);

        #50;
        $display("Simulation Complete.");
        $finish;
    end

endmodule

coal-labs/lab05_2024335/home_tasks/lab5.vcd
$date
	Wed Mar 04 23:12:42 2026
$end
$version
	Icarus Verilog
$end
$timescale
	1ps
$end
$scope module DivisionT1_tb $end
$var wire 8 ! remainder [7:0] $end
$var wire 1 " ready $end
$var wire 8 # quotient [7:0] $end
$var reg 1 $ clk $end
$var reg 8 % dividend [7:0] $end
$var reg 8 & divisor [7:0] $end
$scope module Uut $end
$var wire 1 $ clk $end
$var wire 8 ' dividend [7:0] $end
$var wire 8 ( divisor [7:0] $end
$var reg 1 ) busy $end
$var reg 16 * div_reg [15:0] $end
$var reg 8 + prev_dividend [7:0] $end
$var reg 8 , prev_divisor [7:0] $end
$var reg 8 - quotient [7:0] $end
$var reg 1 " ready $end
$var reg 16 . rem_reg [15:0] $end
$var reg 8 / remainder [7:0] $end
$var reg 4 0 step [3:0] $end
$upscope $end
$upscope $end
$enddefinitions $end
$comment Show the parameter values. $end
$dumpall
$end
#0
$dumpvars
bx 0
b0 /
bx .
b0 -
b0 ,
b0 +
bx *
0)
b0 (
b0 '
b0 &
b0 %
0$
b0 #
0"
b0 !
$end
#5000
1$
#10000
0$
#15000
1$
#20000
b10 &
b10 (
b111 %
b111 '
0$
#25000
1)
b0 0
b100000000 *
b111 .
b10 ,
b111 +
1$
#30000
0$
#35000
b1 0
b10000000 *
1$
#40000
0$
#45000
b10 0
b1000000 *
1$
#50000
0$
#55000
b11 0
b100000 *
1$
#60000
0$
#65000
b100 0
b10000 *
1$
#70000
0$
#75000
b101 0
b1000 *
1$
#80000
0$
#85000
b110 0
b100 *
1$
#90000
0$
#95000
b111 0
b10 *
b1 #
b1 -
b11 .
1$
#100000
0$
#105000
1"
0)
b1000 0
b1 *
b1 !
b1 /
b11 #
b11 -
b1 .
1$
#110000
0$
#115000
1$
#120000
0$
#125000
1$
#130000
0$
#135000
1$
#140000
b11 &
b11 (
b1100100 %
b1100100 '
0$
#145000
0"
1)
b0 0
b0 #
b0 -
b110000000 *
b1100100 .
b11 ,
b1100100 +
1$
#150000
0$
#155000
b1 0
b11000000 *
1$
#160000
0$
#165000
b10 0
b1100000 *
1$
#170000
b1000 &
b1000 (
b101101 %
b101101 '
0$
#175000
b0 0
b10000000000 *
b101101 .
b1000 ,
b101101 +
1$
#180000
0$
#185000
b1 0
b1000000000 *
1$
#190000
0$
#195000
b10 0
b100000000 *
1$
#200000
0$
#205000
b11 0
b10000000 *
1$
#210000
0$
#215000
b100 0
b1000000 *
1$
#220000
0$
#225000
b101 0
b100000 *
1$
#230000
0$
#235000
b110 0
b10000 *
b1 #
b1 -
b1101 .
1$
#240000
0$
#245000
b111 0
b1000 *
b10 #
b10 -
1$
#250000
0$
#255000
1"
0)
b1000 0
b100 *
b101 !
b101 /
b101 #
b101 -
b101 .
1$
#260000
0$
#265000
1$
#270000
0$
#275000
1$
#280000
0$
#285000
1$
#290000
b100 &
b100 (
b1001011 %
b1001011 '
0$
#295000
0"
1)
b0 0
b0 #
b0 -
b1000000000 *
b1001011 .
b100 ,
b1001011 +
1$
#300000
0$
#305000
b1 0
b100000000 *
1$
#310000
0$
#315000
b10 0
b10000000 *
1$
#320000
0$
#325000
b11 0
b1000000 *
1$
#330000
0$
#335000
b100 0
b100000 *
b1 #
b1 -
b1011 .
1$
#340000
0$
#345000
b101 0
b10000 *
b10 #
b10 -
1$
