coal-labs/lab03_2024335/L4T1.v
module register32(
    input clk,
    input reset,
    input [31:0] d,
    output reg [31:0] q
);

// Register updates on rising clock edge
always @(posedge clk or posedge reset) begin
    if (reset)
        q <= 32'b0;     // Clear register
    else
        q <= d;         // Store input data
end

endmodule

coal-labs/lab03_2024335/L4T1_tb.v
`timescale 1ns / 1ps

module register32_tb;

    // Testbench signals (inputs are reg, outputs are wire)
    reg clk;
    reg reset;
    reg [31:0] d;
    wire [31:0] q;

    // Instantiate the 32-bit register (Unit Under Test)
    register32 uut (
        .clk(clk),
        .reset(reset),
        .d(d),
        .q(q)
    );

    // Clock generation: 10ns period
    always #5 clk = ~clk;

    initial begin
        // Initialize signals
        clk = 0;
        reset = 1;
        d = 32'd0;

        // Enable waveform dump
        $dumpfile("register32.vcd");
        $dumpvars(0, register32_tb);

        // Apply reset
        #10 reset = 0;               // Deassert reset

        // Apply first data
        #10 d = 32'd25;              // Load 25
        // q updates at next posedge clk

        // Apply second data
        #10 d = 32'd100;             // Load 100

        // Apply reset again
        #10 reset = 1;
        #10 reset = 0;

        // Apply new data
        #10 d = 32'd999;

        #20 $finish;                 // End simulation
    end

endmodule

coal-labs/register32.vcd
$date
	Fri Feb  6 09:28:02 2026
$end
$version
	Icarus Verilog
$end
$timescale
	1ps
$end
$scope module register32_tb $end
$var wire 32 ! q [31:0] $end
$var reg 1 " clk $end
$var reg 32 # d [31:0] $end
$var reg 1 $ reset $end
$scope module uut $end
$var wire 1 " clk $end
$var wire 32 % d [31:0] $end
$var wire 1 $ reset $end
$var reg 32 & q [31:0] $end
$upscope $end
$upscope $end
$enddefinitions $end
#0
$dumpvars
b0 &
b0 %
1$
b0 #
0"
b0 !
$end
#5000
1"
#10000
0"
0$
#15000
1"
#20000
0"
b11001 #
b11001 %
#25000
b11001 !
b11001 &
1"
#30000
0"
b1100100 #
b1100100 %
#35000
b1100100 !
b1100100 &
1"
#40000
b0 !
b0 &
0"
1$
#45000
1"
#50000
0"
0$
#55000
b1100100 !
b1100100 &
1"
#60000
0"
b1111100111 #
b1111100111 %
#65000
b1111100111 !
b1111100111 &
1"
