coal-labs/lab03_2024335/L4T2.v
module up_counter32(
    input clk,
    input reset,
    output reg [31:0] count
);

always @(posedge clk or posedge reset) begin
    if (reset)
        count <= 32'b0;
    else
        count <= count + 1;  // Increment
end

endmodule

coal-labs/lab03_2024335/L4T2_tb.v
`timescale 1ns / 1ps

module up_counter32_tb;

    // Testbench signals
    reg clk;
    reg reset;
    wire [31:0] count;

    // Instantiate the counter (Unit Under Test)
    up_counter32 uut (
        .clk(clk),
        .reset(reset),
        .count(count)
    );

    // Clock generation: 10ns period
    always #5 clk = ~clk;

    initial begin
        // Initialize signals
        clk = 0;
        reset = 1;

        // Enable waveform dump
        $dumpfile("upcounter.vcd");
        $dumpvars(0, up_counter32_tb);

        // Apply reset
        #10 reset = 0;

        // Let counter run for some cycles
        #100;

        // Apply reset again
        reset = 1;
        #10 reset = 0;

        // Run again
        #50;

        #20 $finish;                 // End simulation
    end

endmodule

coal-labs/random/upcounter.vcd
$date
	Fri Feb 13 09:00:34 2026
$end
$version
	Icarus Verilog
$end
$timescale
	1ps
$end
$scope module up_counter32_tb $end
$var wire 32 ! count [31:0] $end
$var reg 1 " clk $end
$var reg 1 # reset $end
$scope module uut $end
$var wire 1 " clk $end
$var wire 1 # reset $end
$var reg 32 $ count [31:0] $end
$upscope $end
$upscope $end
$enddefinitions $end
#0
$dumpvars
b0 $
1#
0"
b0 !
$end
#5000
1"
#10000
0"
0#
#15000
b1 !
b1 $
1"
#20000
0"
#25000
b10 !
b10 $
1"
#30000
0"
#35000
b11 !
b11 $
1"
#40000
0"
#45000
b100 !
b100 $
1"
#50000
0"
#55000
b101 !
b101 $
1"
#60000
0"
#65000
b110 !
b110 $
1"
#70000
0"
#75000
b111 !
b111 $
1"
#80000
0"
#85000
b1000 !
b1000 $
1"
#90000
0"
#95000
b1001 !
b1001 $
1"
#100000
0"
#105000
b1010 !
b1010 $
1"
#110000
b0 !
b0 $
0"
1#
#115000
1"
#120000
0"
0#
#125000
b1 !
b1 $
1"
#130000
0"
#135000
b10 !
b10 $
1"
#140000
0"
#145000
b11 !
b11 $
1"
#150000
0"
#155000
b100 !
b100 $
1"
#160000
0"
#165000
b101 !
b101 $
1"
#170000
0"
#175000
b110 !
b110 $
1"
#180000
0"
#185000
b111 !
b111 $
1"
