coal-labs/lab04_2024335/task2.v
module mul8u_seq (
    input        clk,
    input        rst,
    input  [7:0] a,
    input  [7:0] b,
    output reg [15:0] y,
    output reg   ready
);

    reg [15:0] multiplicand;
    reg [7:0]  multiplier;
    reg [3:0]  count;

    always @(posedge clk or posedge rst) begin
        if (rst) begin
            multiplicand <= 0;
            multiplier   <= 0;
            y            <= 0;
            count        <= 0;
            ready        <= 0;
        end else begin
            if (count == 0) begin
                // load operands
                multiplicand <= {8'b0, a};
                multiplier   <= b;
                y            <= 0;
                ready        <= 0;
                count        <= 1;
            end else if (count <= 8) begin
                if (multiplier[0])
                    y <= y + multiplicand;

                multiplicand <= multiplicand << 1;
                multiplier   <= multiplier >> 1;
                count        <= count + 1;

                if (count == 8)
                    ready <= 1;
            end else begin
                // Idle: hold result until reset
                ready <= 1;
            end
        end
    end
endmodule

coal-labs/lab04_2024335/task2_tb.v
module tb_mul8u_seq;

    reg clk, rst;
    reg [7:0] a, b;
    wire [15:0] y;
    wire ready;

    mul8u_seq DUT (clk, rst, a, b, y, ready);

    always #5 clk = ~clk;

    initial begin
        $dumpfile("task2_tb.vcd");
        $dumpvars(0, tb_mul8u_seq);
        clk = 0; rst = 1;
        a = 0; b = 0;
        #20 rst = 0;

        // Test 1: 15 * 3 = 45
        a = 15; b = 3;
        #100;
        $display("Test 1: %0d * %0d = %0d (expected 45)", a, b, y);

        // Reset between tests
        rst = 1; #20; rst = 0;

        // Test 2: 255 * 255 = 65025
        a = 255; b = 255;
        #100;
        $display("Test 2: %0d * %0d = %0d (expected 65025)", a, b, y);

        // Reset between tests
        rst = 1; #20; rst = 0;

        // Test 3: 128 * 2 = 256
        a = 128; b = 2;
        #100;
        $display("Test 3: %0d * %0d = %0d (expected 256)", a, b, y);

        $finish;
    end
endmodule

coal-labs/lab04_2024335/task2_tb.vcd
$date
	Fri Feb 20 10:29:45 2026
$end
$version
	Icarus Verilog
$end
$timescale
	1s
$end
$scope module tb_mul8u_seq $end
$var wire 16 ! y [15:0] $end
$var wire 1 " ready $end
$var reg 8 # a [7:0] $end
$var reg 8 $ b [7:0] $end
$var reg 1 % clk $end
$var reg 1 & rst $end
$scope module DUT $end
$var wire 8 ' a [7:0] $end
$var wire 8 ( b [7:0] $end
$var wire 1 % clk $end
$var wire 1 & rst $end
$var reg 4 ) count [3:0] $end
$var reg 16 * multiplicand [15:0] $end
$var reg 8 + multiplier [7:0] $end
$var reg 1 " ready $end
$var reg 16 , y [15:0] $end
$upscope $end
$upscope $end
$enddefinitions $end
#0
$dumpvars
b0 ,
b0 +
b0 *
b0 )
b0 (
b0 '
1&
0%
b0 $
b0 #
0"
b0 !
$end
#5
1%
#10
0%
b11 $
b11 (
b1111 #
b1111 '
0&
#15
b1 )
b11 +
b1111 *
1%
#20
0%
#25
b10 )
b1 +
b11110 *
b1111 !
b1111 ,
1%
#30
0%
#35
b11 )
b0 +
b111100 *
b101101 !
b101101 ,
1%
#40
0%
#45
b100 )
b1111000 *
1%
#50
0%
#55
b101 )
b11110000 *
1%
#60
0%
#65
b110 )
b111100000 *
1%
#70
0%
#75
b111 )
b1111000000 *
1%
#80
0%
#85
b1000 )
b11110000000 *
1%
#90
0%
#95
1"
b1001 )
b111100000000 *
1%
#100
0%
#105
1%
#110
0%
b11111111 $
b11111111 (
b11111111 #
b11111111 '
